{
    "Serilog": {
        "WriteTo": {
            "EmailSink": {
                "Name": "Email",
                "Args": {
                    "connectionInfo": {
                        "FromEmail": "your-sender@email.com",
                        "ToEmail": "your-recipient@email.com",
                        "MailServer": "your-email-server",
                        "EmailSubject": "your-email-subject",
                        "Port": 25
                    },
                    "restrictedToMinimumLevel": "Error",
                    "outputTemplate": "{Timestamp:yyyy-MM-dd HH:mm:ssz} {MachineName} {SourceContext} {ThreadId} [{Level:w3}] {Message:lj}{NewLine}{Exception}"
                }
            },
            "SlackSink": {
                "Name": "Slack",
                "Args": {
                    "SlackSinkOptions": {
                        "WebHookUrl": "SECRETS ARE STORED IN SERVER ENVIRONMENT VARIABLES",
                        "BatchSizeLimit": 20,
                        "ShowDefaultAttachments": false,
                        "ShowPropertyAttachments": false,
                        "ShowExceptionAttachments": false
                    },
                    "restrictedToMinimumLevel": "Error",
                    "outputTemplate": "Albatross.Templates:{Timestamp:yyyy-MM-dd HH:mm:ssz} {MachineName} {SourceContext} {ThreadId} [{Level:w3}] {Message:lj}"
                }
            }
        }
    }
}